xtyle-0.1.10.dist-info/METADATA
xtyle-0.1.10.dist-info/WHEEL
xtyle-0.1.10.dist-info/licenses/LICENSE
xtyle/__init__.py
xtyle/babel.min.js
xtyle/client.py
xtyle/core.py
xtyle/custom.js
xtyle/external_plugins.py
xtyle/live_code/__init__.py
xtyle/live_code/component-samples/base.html
xtyle/live_code/component-samples/code.tsx
xtyle/live_code/component-samples/docs.tsx
xtyle/live_code/component-samples/props.tsx
xtyle/live_code/component-samples/style.scss
xtyle/live_code/core.py
xtyle/live_code/environment.py
xtyle/live_code/esmodules.py
xtyle/live_code/get_xtyle.py
xtyle/live_code/plugin_gzip.py
xtyle/live_code/sample-codes/globals.d.ts
xtyle/live_code/sample-codes/index.html
xtyle/live_code/sample-codes/index.ts
xtyle/live_code/sample-codes/package.json
xtyle/live_code/sample-codes/postcss.config.cjs
xtyle/live_code/sample-codes/preview.ts
xtyle/live_code/sample-codes/rollup.config.js
xtyle/live_code/sample-codes/tsconfig.json
xtyle/live_code/sample-codes/tsconfig.node.json
xtyle/live_code/sample-codes/vite-env.d.ts
xtyle/live_code/sample-codes/vite.config.js
xtyle/live_code/sample-codes/xtyle_build.mjs
xtyle/live_code/sample-codes/xtyle_component.mjs
xtyle/live_code/sample.py
xtyle/live_code/static.py
xtyle/live_code/templates-tools/dev.html
xtyle/live_code/templates-tools/init.html
xtyle/live_code/templates.py
xtyle/live_code/types.py
xtyle/live_code/typescript_tools.py
xtyle/prettier-full.min.js
xtyle-0.1.10.dist-info/RECORD
