Metadata-Version: 2.1
Name: xtyle
Version: 0.1.10
Summary: Xtyle (Toolkit)
Author-Email: hlop3z <23062270+hlop3z@users.noreply.github.com>
License: MIT
Project-URL: Homepage, https://github.com/hlop3z/xtyle-python/
Requires-Python: >=3.10
Requires-Dist: jinja2>=3.1.2
Requires-Dist: py-mini-racer>=0.6.0; extra == "debug"
Requires-Dist: libsass>=0.22.0; extra == "debug"
Requires-Dist: requests>=2.31.0; extra == "debug"
Requires-Dist: sqlow>=0.1.5; extra == "debug"
Provides-Extra: debug
